mysql_type/__init__.py
mysql_type/py.typed
mysql_type-0.1.4.dist-info/LICENSE
mysql_type-0.1.4.dist-info/METADATA
mysql_type-0.1.4.dist-info/WHEEL
mysql_type-0.1.4.dist-info/top_level.txt
mysql_type-0.1.4.dist-info/RECORD
